{
  "data": {
    "username": "gsimnett0",
    "myFile": "users/gsimnett0-TbObbUKQ",
    "accounts": [
      {
        "name": "Lönekonto",
        "balance": 1005162,
        "history": [
          {
            "label": "vi skickar 1 till 111-1111",
            "amount": -1,
            "time": "2019-04-25 10:07"
          },
          {
            "label": "vi skickar 1 till 111-1111",
            "amount": -1,
            "time": "2019-04-25 10:07",
            "accountName": "Lönekonto"
          },
          {
            "label": "vi skickar 1 till 111-1111",
            "amount": -1,
            "time": "2019-04-25 10:07",
            "accountName": "Lönekonto"
          },
          {
            "label": "vi skickar 1 till 111-1111",
            "amount": -1,
            "time": "2019-04-25 10:04",
            "accountName": "Lönekonto"
          },
          {
            "label": "vi skickar 1 till 111-1111",
            "amount": -1,
            "time": "2019-04-25 10:04",
            "accountName": "Lönekonto"
          },
          {
            "label": "vi skickar 1 till 111-1111",
            "amount": -1,
            "time": "2019-04-25 10:03",
            "accountName": "Lönekonto"
          },
          {
            "label": "vi skickar 1 till 111-1111",
            "amount": -1,
            "time": "2019-04-25 10:00",
            "accountName": "Lönekonto"
          },
          {
            "label": "vi skickar 1 till 111-1111",
            "amount": -1,
            "time": "2019-04-25 10:00",
            "accountName": "Lönekonto"
          },
          {
            "label": "vi skickar 1 till 111-1111",
            "amount": -1,
            "time": "2019-04-25 10:00",
            "accountName": "Lönekonto"
          },
          {
            "label": "vi skickar 1 till 111-1111",
            "amount": -1,
            "time": "2019-04-25 09:41",
            "accountName": "Lönekonto"
          },
          {
            "label": "vi skickar 1 till 111-1111",
            "amount": -1,
            "time": "2019-04-25 09:41",
            "accountName": "Lönekonto"
          },
          {
            "label": "vi skickar 1 till 111-1111",
            "amount": -1,
            "time": "2019-04-25 09:41",
            "accountName": "Lönekonto"
          },
          {
            "label": "vi skickar 1 till 111-1111",
            "amount": -1,
            "time": "2019-04-25 09:38",
            "accountName": "Lönekonto"
          },
          {
            "label": "vi skickar 1 till 111-1111",
            "amount": -1,
            "time": "2019-04-25 09:38",
            "accountName": "Lönekonto"
          },
          {
            "label": "vi skickar 1 till 111-1111",
            "amount": -1,
            "time": "2019-04-25 09:38",
            "accountName": "Lönekonto"
          },
          {
            "label": "vi skickar 1 till 111-1111",
            "amount": -1,
            "time": "2019-04-25 09:21",
            "accountName": "Lönekonto"
          },
          {
            "label": "vi skickar 1 till 111-1111",
            "amount": -1,
            "time": "2019-04-25 09:20",
            "accountName": "Lönekonto"
          },
          {
            "label": "vi skickar 1 till 111-1111",
            "amount": -1,
            "time": "2019-04-25 09:20",
            "accountName": "Lönekonto"
          },
          {
            "label": "vi skickar 1 till 111-1111",
            "amount": -1,
            "time": "2019-04-25 09:17",
            "accountName": "Lönekonto"
          },
          {
            "label": "vi skickar 1 till 111-1111",
            "amount": -1,
            "time": "2019-04-25 09:17",
            "accountName": "Lönekonto"
          },
          {
            "label": "vi skickar 1 till 111-1111",
            "amount": -1,
            "time": "2019-04-25 09:17",
            "accountName": "Lönekonto"
          },
          {
            "label": "vi skickar 1 till 111-1111",
            "amount": -1,
            "time": "2019-04-25 09:14",
            "accountName": "Lönekonto"
          },
          {
            "label": "vi skickar 1 till 111-1111",
            "amount": -1,
            "time": "2019-04-25 09:14",
            "accountName": "Lönekonto"
          },
          {
            "label": "vi skickar 1 till 111-1111",
            "amount": -1,
            "time": "2019-04-25 09:14",
            "accountName": "Lönekonto"
          },
          {
            "label": "vi skickar 1 till 111-1111",
            "amount": -1,
            "time": "2019-04-25 09:04",
            "accountName": "Lönekonto"
          },
          {
            "label": "vi skickar 1 till 111-1111",
            "amount": -1,
            "time": "2019-04-25 09:04",
            "accountName": "Lönekonto"
          },
          {
            "label": "vi skickar 1 till 111-1111",
            "amount": -1,
            "time": "2019-04-25 09:03",
            "accountName": "Lönekonto"
          },
          {
            "label": "vi skickar 1 till 111-1111",
            "amount": -1,
            "time": "2019-04-25 08:47",
            "accountName": "Lönekonto"
          },
          {
            "label": "vi skickar 1 till 111-1111",
            "amount": -1,
            "time": "2019-04-25 08:47",
            "accountName": "Lönekonto"
          },
          {
            "label": "vi skickar 1 till 111-1111",
            "amount": -1,
            "time": "2019-04-25 08:46",
            "accountName": "Lönekonto"
          },
          {
            "label": "vi skickar 1 till 111-1111",
            "amount": -1,
            "time": "2019-04-24 13:15",
            "accountName": "Lönekonto"
          },
          {
            "label": "vi skickar 1 till 111-1111",
            "amount": -1,
            "time": "2019-04-24 13:15",
            "accountName": "Lönekonto"
          },
          {
            "label": "vi skickar 1 till 111-1111",
            "amount": -1,
            "time": "2019-04-24 12:48",
            "accountName": "Lönekonto"
          },
          {
            "label": "vi skickar 1 till 111-1111",
            "amount": -1,
            "time": "2019-04-24 12:48",
            "accountName": "Lönekonto"
          },
          {
            "label": "vi skickar 1 till 111-1111",
            "amount": -1,
            "time": "2019-04-24 12:47",
            "accountName": "Lönekonto"
          },
          {
            "label": "vi skickar 1 till 111-1111",
            "amount": -1,
            "time": "2019-04-24 12:42",
            "accountName": "Lönekonto"
          },
          {
            "label": "vi skickar 1 till 111-1111",
            "amount": -1,
            "time": "2019-04-24 12:42",
            "accountName": "Lönekonto"
          },
          {
            "label": "vi skickar 1 till 111-1111",
            "amount": -1,
            "time": "2019-04-24 12:35",
            "accountName": "Lönekonto"
          },
          {
            "label": "vi skickar 1 till 111-1111",
            "amount": -1,
            "time": "2019-04-24 12:35",
            "accountName": "Lönekonto"
          },
          {
            "label": "vi skickar 1 till 111-1111",
            "amount": -1,
            "time": "2019-04-24 12:34",
            "accountName": "Lönekonto"
          },
          {
            "label": "vi skickar 1 till 111-1111",
            "amount": -1,
            "time": "2019-04-24 12:29",
            "accountName": "Lönekonto"
          },
          {
            "label": "vi skickar 1 till 111-1111",
            "amount": -1,
            "time": "2019-04-24 12:29",
            "accountName": "Lönekonto"
          },
          {
            "label": "vi skickar 1 till 111-1111",
            "amount": -1,
            "time": "2019-04-24 12:29",
            "accountName": "Lönekonto"
          },
          {
            "label": "vi skickar 1 till 111-1111",
            "amount": -1,
            "time": "2019-04-24 12:20",
            "accountName": "Lönekonto"
          },
          {
            "label": "vi skickar 1 till 111-1111",
            "amount": -1,
            "time": "2019-04-24 12:20",
            "accountName": "Lönekonto"
          },
          {
            "label": "vi skickar 1 till 111-1111",
            "amount": -1,
            "time": "2019-04-24 12:20",
            "accountName": "Lönekonto"
          },
          {
            "label": "vi skickar 1 till 111-1111",
            "amount": -1,
            "time": "2019-04-24 12:17",
            "accountName": "Lönekonto"
          },
          {
            "label": "vi skickar 1 till 111-1111",
            "amount": -1,
            "time": "2019-04-24 12:17",
            "accountName": "Lönekonto"
          },
          {
            "label": "vi skickar 1 till 111-1111",
            "amount": -1,
            "time": "2019-04-24 12:17",
            "accountName": "Lönekonto"
          },
          {
            "label": "vi skickar 1 till 111-1111",
            "amount": -1,
            "time": "2019-04-24 12:12",
            "accountName": "Lönekonto"
          },
          {
            "label": "vi skickar 1 till 111-1111",
            "amount": -1,
            "time": "2019-04-24 12:12",
            "accountName": "Lönekonto"
          },
          {
            "label": "vi skickar 1 till 111-1111",
            "amount": -1,
            "time": "2019-04-24 12:12",
            "accountName": "Lönekonto"
          },
          {
            "label": "vi skickar 1 till 111-1111",
            "amount": -1,
            "time": "2019-04-24 12:09",
            "accountName": "Lönekonto"
          },
          {
            "label": "vi skickar 1 till 111-1111",
            "amount": -1,
            "time": "2019-04-24 12:08",
            "accountName": "Lönekonto"
          },
          {
            "label": "vi skickar 1 till 111-1111",
            "amount": -1,
            "time": "2019-04-24 12:08",
            "accountName": "Lönekonto"
          },
          {
            "label": "vi skickar 1 till 111-1111",
            "amount": -1,
            "time": "2019-04-24 10:10",
            "accountName": "Lönekonto"
          },
          {
            "label": "vi skickar 1 till 111-1111",
            "amount": -1,
            "time": "2019-04-24 10:10",
            "accountName": "Lönekonto"
          },
          {
            "label": "vi skickar 1 till 111-1111",
            "amount": -1,
            "time": "2019-04-24 10:10",
            "accountName": "Lönekonto"
          },
          {
            "label": "vi skickar 1 till 111-1111",
            "amount": -1,
            "time": "2019-04-24 10:09",
            "accountName": "Lönekonto"
          },
          {
            "label": "vi skickar 1 till 111-1111",
            "amount": -1,
            "time": "2019-04-24 10:08",
            "accountName": "Lönekonto"
          },
          {
            "label": "vi skickar 1 till 111-1111",
            "amount": -1,
            "time": "2019-04-24 10:08",
            "accountName": "Lönekonto"
          },
          {
            "label": "vi skickar 1 till 111-1111",
            "amount": -1,
            "time": "2019-04-24 10:08",
            "accountName": "Lönekonto"
          },
          {
            "label": "vi skickar 1 till 111-1111",
            "amount": -1,
            "time": "2019-04-24 10:07",
            "accountName": "Lönekonto"
          },
          {
            "label": "vi skickar 1 till 111-1111",
            "amount": -1,
            "time": "2019-04-24 10:07",
            "accountName": "Lönekonto"
          },
          {
            "label": "vi skickar 1 till 111-1111",
            "amount": -1,
            "time": "2019-04-24 09:45",
            "accountName": "Lönekonto"
          },
          {
            "label": "vi skickar 1 till 111-1111",
            "amount": -1,
            "time": "2019-04-24 09:45",
            "accountName": "Lönekonto"
          },
          {
            "label": "vi skickar 1 till 111-1111",
            "amount": -1,
            "time": "2019-04-24 09:44",
            "accountName": "Lönekonto"
          },
          {
            "label": "vi skickar 1 till 111-1111",
            "amount": -1,
            "time": "2019-04-24 09:38",
            "accountName": "Lönekonto"
          },
          {
            "label": "vi skickar 1 till 111-1111",
            "amount": -1,
            "time": "2019-04-24 09:38",
            "accountName": "Lönekonto"
          },
          {
            "label": "vi skickar 1 till 111-1111",
            "amount": -1,
            "time": "2019-04-24 09:38",
            "accountName": "Lönekonto"
          },
          {
            "label": "vi skickar 1 till 111-1111",
            "amount": -1,
            "time": "2019-04-24 09:37",
            "accountName": "Lönekonto"
          },
          {
            "label": "vi skickar 1 till 111-1111",
            "amount": -1,
            "time": "2019-04-24 09:37",
            "accountName": "Lönekonto"
          },
          {
            "label": "vi skickar 1 till 111-1111",
            "amount": -1,
            "time": "2019-04-24 09:37",
            "accountName": "Lönekonto"
          },
          {
            "label": "vi skickar 1 till 111-1111",
            "amount": -1,
            "time": "2019-04-24 09:36",
            "accountName": "Lönekonto"
          },
          {
            "label": "vi skickar 1 till 111-1111",
            "amount": -1,
            "time": "2019-04-24 09:36",
            "accountName": "Lönekonto"
          },
          {
            "label": "vi skickar 1 till 111-1111",
            "amount": -1,
            "time": "2019-04-24 09:36",
            "accountName": "Lönekonto"
          },
          {
            "label": "vi skickar 1 till 111-1111",
            "amount": -1,
            "time": "2019-04-24 09:33",
            "accountName": "Lönekonto"
          },
          {
            "label": "vi skickar 1 till 111-1111",
            "amount": -1,
            "time": "2019-04-24 09:32",
            "accountName": "Lönekonto"
          },
          {
            "label": "vi skickar 1 till 111-1111",
            "amount": -1,
            "time": "2019-04-24 09:32",
            "accountName": "Lönekonto"
          },
          {
            "label": "vi skickar 1 till 111-1111",
            "amount": -1,
            "time": "2019-04-24 09:29",
            "accountName": "Lönekonto"
          },
          {
            "label": "vi skickar 1 till 111-1111",
            "amount": -1,
            "time": "2019-04-24 09:29",
            "accountName": "Lönekonto"
          },
          {
            "label": "vi skickar 1 till 111-1111",
            "amount": -1,
            "time": "2019-04-24 09:28",
            "accountName": "Lönekonto"
          },
          {
            "label": "vi skickar 1 till 111-1111",
            "amount": -1,
            "time": "2019-04-24 09:25",
            "accountName": "Lönekonto"
          },
          {
            "label": "vi skickar 1 till 111-1111",
            "amount": -1,
            "time": "2019-04-24 09:25",
            "accountName": "Lönekonto"
          },
          {
            "label": "vi skickar 1 till 111-1111",
            "amount": -1,
            "time": "2019-04-24 09:21",
            "accountName": "Lönekonto"
          },
          {
            "label": "vi skickar 1 till 111-1111",
            "amount": -1,
            "time": "2019-04-24 09:21",
            "accountName": "Lönekonto"
          },
          {
            "label": "vi skickar 1 till 111-1111",
            "amount": -1,
            "time": "2019-04-24 09:21",
            "accountName": "Lönekonto"
          },
          {
            "label": "vi skickar 1 till 111-1111",
            "amount": -1,
            "time": "2019-04-24 09:20",
            "accountName": "Lönekonto"
          },
          {
            "label": "vi skickar 1 till 111-1111",
            "amount": -1,
            "time": "2019-04-24 09:20",
            "accountName": "Lönekonto"
          },
          {
            "label": "vi skickar 1 till 111-1111",
            "amount": -1,
            "time": "2019-04-24 09:20",
            "accountName": "Lönekonto"
          },
          {
            "label": "vi skickar 1 till 111-1111",
            "amount": -1,
            "time": "2019-04-24 09:08",
            "accountName": "Lönekonto"
          },
          {
            "label": "vi skickar 1 till 111-1111",
            "amount": -1,
            "time": "2019-04-24 09:08",
            "accountName": "Lönekonto"
          },
          {
            "label": "vi skickar 1 till 111-1111",
            "amount": -1,
            "time": "2019-04-24 09:08",
            "accountName": "Lönekonto"
          },
          {
            "label": "vi skickar 1 till 111-1111",
            "amount": -1,
            "time": "2019-04-24 08:55",
            "accountName": "Lönekonto"
          },
          {
            "label": "vi skickar 1 till 111-1111",
            "amount": -1,
            "time": "2019-04-24 08:55",
            "accountName": "Lönekonto"
          },
          {
            "label": "vi skickar 1 till 111-1111",
            "amount": -1,
            "time": "2019-04-24 08:55",
            "accountName": "Lönekonto"
          },
          {
            "label": "vi skickar 1 till 111-1111",
            "amount": -1,
            "time": "2019-04-23 21:11",
            "accountName": "Lönekonto"
          },
          {
            "label": "vi skickar 1 till 111-1111",
            "amount": -1,
            "time": "2019-04-23 21:11",
            "accountName": "Lönekonto"
          },
          {
            "label": "vi skickar 1 till 111-1111",
            "amount": -1,
            "time": "2019-04-23 21:11",
            "accountName": "Lönekonto"
          },
          {
            "label": "vi skickar 1 till 111-1111",
            "amount": -1,
            "time": "2019-04-23 21:08",
            "accountName": "Lönekonto"
          },
          {
            "label": "vi skickar 1 till 111-1111",
            "amount": -1,
            "time": "2019-04-23 21:07",
            "accountName": "Lönekonto"
          },
          {
            "label": "vi skickar 1 till 111-1111",
            "amount": -1,
            "time": "2019-04-23 20:31",
            "accountName": "Lönekonto"
          },
          {
            "label": "vi skickar 1 till 111-1111",
            "amount": -1,
            "time": "2019-04-23 20:31",
            "accountName": "Lönekonto"
          },
          {
            "label": "vi skickar 1 till 111-1111",
            "amount": -1,
            "time": "2019-04-23 20:31",
            "accountName": "Lönekonto"
          },
          {
            "label": "vi skickar 1 till 111-1111",
            "amount": -1,
            "time": "2019-04-23 20:28",
            "accountName": "Lönekonto"
          },
          {
            "label": "vi skickar 1 till 111-1111",
            "amount": -1,
            "time": "2019-04-23 20:23",
            "accountName": "Lönekonto"
          },
          {
            "label": "vi skickar 1 till 111-1111",
            "amount": -1,
            "time": "2019-04-23 20:17",
            "accountName": "Lönekonto"
          },
          {
            "label": "vi skickar 1 till 111-1111",
            "amount": -1,
            "time": "2019-04-23 20:16",
            "accountName": "Lönekonto"
          },
          {
            "label": "vi skickar 1 till 111-1111",
            "amount": -1,
            "time": "2019-04-23 19:57",
            "accountName": "Lönekonto"
          },
          {
            "label": "vi skickar 1 till 111-1111",
            "amount": -1,
            "time": "2019-04-23 19:55",
            "accountName": "Lönekonto"
          },
          {
            "label": "vi skickar 1 till 111-1111",
            "amount": -1,
            "time": "2019-04-23 19:52",
            "accountName": "Lönekonto"
          },
          {
            "label": "vi skickar 1 till 111-1111",
            "amount": -1,
            "time": "2019-04-23 19:48",
            "accountName": "Lönekonto"
          },
          {
            "label": "vi skickar 1 till 111-1111",
            "amount": -1,
            "time": "4/23/2019, 7:34 PM",
            "accountName": "Lönekonto"
          },
          {
            "label": "vi skickar 1 till 111-1111",
            "amount": -1,
            "time": "2019-04-23 19:23",
            "accountName": "Lönekonto"
          },
          {
            "label": "vi skickar 1 till 111-1111",
            "amount": -1,
            "time": "2019-04-23 19:22",
            "accountName": "Lönekonto"
          },
          {
            "label": "",
            "amount": -1,
            "time": "4/23/2019, 7:19 PM",
            "accountName": "Lönekonto"
          },
          {
            "label": "test",
            "amount": -1,
            "time": "4/18/2019, 3:51 PM",
            "accountName": "Lönekonto"
          },
          {
            "label": "test 1234 !\"#¤",
            "amount": -5000,
            "time": "4/18/2019, 3:44 PM",
            "accountName": "Lönekonto"
          },
          {
            "label": "5000 kr",
            "amount": -5000,
            "time": "4/18/2019, 3:03 PM",
            "accountName": "Lönekonto"
          },
          {
            "label": "5000 kr",
            "amount": -5000,
            "time": "4/18/2019, 2:54 PM",
            "accountName": "Lönekonto"
          },
          {
            "label": "skatteåterbärring",
            "amount": 1000000,
            "time": "4/18/2019, 2:52 PM",
            "accountName": "Lönekonto"
          },
          {
            "label": "lön",
            "amount": 19999,
            "time": "4/18/2019, 1:04 PM",
            "accountName": "Lönekonto"
          },
          {
            "label": "Kaffe",
            "amount": -20,
            "time": "4/18/2019, 1:04 PM",
            "accountName": "Lönekonto"
          },
          {
            "label": "skatt är stöld",
            "amount": -150,
            "time": "4/18/2019, 11:05 AM",
            "accountName": "Lönekonto"
          },
          {
            "label": "swish",
            "amount": 450,
            "time": "4/18/2019, 10:54 AM",
            "accountName": "Lönekonto"
          },
          {
            "label": "swish",
            "amount": 450,
            "time": "4/18/2019, 10:54 AM",
            "accountName": "Lönekonto"
          },
          {
            "label": "swish",
            "amount": 450,
            "time": "4/18/2019, 10:54 AM",
            "accountName": "Lönekonto"
          },
          {
            "label": "swish",
            "amount": 450,
            "time": "4/18/2019, 10:54 AM",
            "accountName": "Lönekonto"
          },
          {
            "label": "swish",
            "amount": 450,
            "time": "4/18/2019, 10:54 AM",
            "accountName": "Lönekonto"
          },
          {
            "label": "swish",
            "amount": 450,
            "time": "4/18/2019, 10:54 AM",
            "accountName": "Lönekonto"
          },
          {
            "label": "swish",
            "amount": 450,
            "time": "4/18/2019, 10:54 AM",
            "accountName": "Lönekonto"
          },
          {
            "label": "swish för kinamat med folk från skolan.swish för kinamat med folk från skolan.swish för kinamat med folk från skolan.swish för kinamat med folk från skolan.swish för kinamat med folk från skolan.",
            "amount": 450,
            "time": "4/18/2019, 10:54 AM",
            "accountName": "Lönekonto"
          }
        ],
        "accountNumber": "2860-802090",
        "⚙": "Account"
      },
      {
        "name": "pension",
        "balance": 0,
        "history": [],
        "accountNumber": "5680-858757",
        "⚙": "Account"
      },
      {
        "name": "semester",
        "balance": 0,
        "history": [],
        "accountNumber": "7694-035658",
        "⚙": "Account"
      }
    ],
    "⚙": "User"
  }
}